messagerie/__init__.py
messagerie/services.py
Messagerie-0.2.3.dist-info/RECORD
Messagerie-0.2.3.dist-info/DESCRIPTION.rst
Messagerie-0.2.3.dist-info/METADATA
Messagerie-0.2.3.dist-info/metadata.json
Messagerie-0.2.3.dist-info/top_level.txt
Messagerie-0.2.3.dist-info/WHEEL
