Metadata-Version: 2.0
Name: Messagerie
Version: 0.2.3
Summary: Custom wrapper to aws services
Home-page: https://github.com/stikks/messagerie
Author: stikks
Author-email: styccs@gmail.com
License: UNKNOWN
Platform: UNKNOWN
Requires-Dist: requests
Requires-Dist: boto3
Requires-Dist: pyshorteners
